chemmltoolkit/__init__.py
chemmltoolkit/__version__.py
chemmltoolkit/data/__init__.py
chemmltoolkit/data/pipelines/__init__.py
chemmltoolkit/data/pipelines/dataPipeline.py
chemmltoolkit/data/pipelines/moleculePipeline.py
chemmltoolkit/data/quantities/__init__.py
chemmltoolkit/data/quantities/_constants.py
chemmltoolkit/data/quantities/maths.py
chemmltoolkit/data/quantities/quantity.py
chemmltoolkit/data/quantities/string_conv.py
chemmltoolkit/features/__init__.py
chemmltoolkit/features/atomFeatures.py
chemmltoolkit/features/atomFeaturiser.py
chemmltoolkit/features/bondFeatures.py
chemmltoolkit/features/bondFeaturiser.py
chemmltoolkit/features/coreFeatures.py
chemmltoolkit/features/decorators.py
chemmltoolkit/features/featuriser.py
chemmltoolkit/features/graphFeaturiser.py
chemmltoolkit/features/moleculeFeatures.py
chemmltoolkit/features/moleculeFeaturiser.py
chemmltoolkit/features/utils.py
chemmltoolkit/processing/__init__.py
chemmltoolkit/processing/adjacency_ops.py
chemmltoolkit/processing/conformerGenerator.py
chemmltoolkit/processing/mols.py
chemmltoolkit/processing/smiles.py
chemmltoolkit/proteins/__init__.py
chemmltoolkit/proteins/alignment.py
chemmltoolkit/proteins/interactions.py
chemmltoolkit/proteins/molecule.py
chemmltoolkit/proteins/protein.py
chemmltoolkit/tensorflow/__init__.py
chemmltoolkit/tensorflow/utils.py
chemmltoolkit/tensorflow/callbacks/__init__.py
chemmltoolkit/tensorflow/callbacks/variableScheduler.py
chemmltoolkit/tensorflow/distribute/__init__.py
chemmltoolkit/tensorflow/distribute/determine_strategy.py
chemmltoolkit/tensorflow/graph/__init__.py
chemmltoolkit/tensorflow/graph/io.py
chemmltoolkit/tensorflow/graph/tensorGraph.py
chemmltoolkit/tensorflow/graph/tensorGraphInput.py
chemmltoolkit/tensorflow/layers/__init__.py
chemmltoolkit/tensorflow/layers/graphConv.py
chemmltoolkit/tensorflow/layers/oneHotEncoding.py
chemmltoolkit/tensorflow/layers/shiftTensor.py
chemmltoolkit/tensorflow/layers/preprocessing/__init__.py
chemmltoolkit-0.1.1.dev9.dist-info/LICENSE
chemmltoolkit-0.1.1.dev9.dist-info/METADATA
chemmltoolkit-0.1.1.dev9.dist-info/WHEEL
chemmltoolkit-0.1.1.dev9.dist-info/top_level.txt
chemmltoolkit-0.1.1.dev9.dist-info/RECORD
