Metadata-Version: 2.1
Name: chemmltoolkit
Version: 0.1.1.dev9
Summary: Useful functionality for machine learning in chemistry
Home-page: https://github.com/Andy-Wilkinson/ChemMLToolkit
Author: Andrew Wilkinson
License: MIT License
